LICENSE
MANIFEST.in
README.md
README.rst
setup.py
nanoQC/__init__.py
nanoQC/nanoQC.py
nanoQC/version.py
nanoQC.egg-info/PKG-INFO
nanoQC.egg-info/SOURCES.txt
nanoQC.egg-info/dependency_links.txt
nanoQC.egg-info/entry_points.txt
nanoQC.egg-info/requires.txt
nanoQC.egg-info/top_level.txt
scripts/test.sh