Metadata-Version: 2.1
Name: nanoQC
Version: 0.10.0
Summary: Create fastQC-like plots for Oxford Nanopore sequencing data
Home-page: https://github.com/wdecoster/nanoQC
Author: Wouter De Coster
Author-email: decosterwouter@gmail.com
License: GPLv3
Keywords: nanopore sequencing statistics
Classifier: Development Status :: 4 - Beta
Classifier: Intended Audience :: Science/Research
Classifier: Topic :: Scientific/Engineering :: Bio-Informatics
Classifier: License :: OSI Approved :: MIT License
Classifier: Programming Language :: Python :: 3
Classifier: Programming Language :: Python :: 3.3
Classifier: Programming Language :: Python :: 3.4
Classifier: Programming Language :: Python :: 3.5
Requires-Python: >=3
License-File: LICENSE
